quant1x/qmt/__init__.py
quant1x/qmt/__main__.py
quant1x/qmt/callback.py
quant1x/qmt/context.py
quant1x/qmt/core.py
quant1x/qmt/env.py
quant1x/qmt/logger.py
quant1x/qmt/market.py
quant1x/qmt/server.py
quant1x/qmt/test_client.py
quant1x/qmt/thinktrader.py
quant1x/qmt/trade_pb2.py
quant1x/qmt/utils.py
quant1x_qmt-1.3.7.dist-info/LICENSE
quant1x_qmt-1.3.7.dist-info/METADATA
quant1x_qmt-1.3.7.dist-info/WHEEL
quant1x_qmt-1.3.7.dist-info/entry_points.txt
quant1x_qmt-1.3.7.dist-info/top_level.txt
quant1x_qmt-1.3.7.dist-info/RECORD
