Metadata-Version: 2.1
Name: quant1x-qmt
Version: 1.3.7
Summary: Quant1X程序化交易
Home-page: https://gitee.com/quant1x/qmt
Author: WangFeng
Author-email: wangfengxy@sina.cn
License: MIT license
Keywords: quant1x qmt
Classifier: Development Status :: 2 - Pre-Alpha
Classifier: Intended Audience :: Developers
Classifier: License :: OSI Approved :: MIT License
Classifier: Natural Language :: English
Classifier: Programming Language :: Python :: 3
Classifier: Programming Language :: Python :: 3.8
Classifier: Programming Language :: Python :: 3.9
Classifier: Programming Language :: Python :: 3.10
Classifier: Programming Language :: Python :: 3.11
License-File: LICENSE
Requires-Dist: setuptools ~=68.2.2
Requires-Dist: future ~=0.18.3
Requires-Dist: numpy ~=1.26.0
Requires-Dist: pandas ~=2.1.1
Requires-Dist: PyYAML ~=6.0.1
Requires-Dist: pywin32 ==306
Requires-Dist: uvicorn ==0.18.1
Requires-Dist: fastapi ~=0.103.1
Requires-Dist: path ~=16.7.1
Requires-Dist: requests ==2.31.0
Requires-Dist: loguru ~=0.7.2
